aios/README.md
aios/__init__.py
aios/command_executor.py
aios/command_parser.py
aios/context/README.md
aios/context/__init__.py
aios/context/base.py
aios/context/simple_context.py
aios/llm_kernel/README.md
aios/llm_kernel/llms.py
aios/llm_kernel/llm_classes/__init__.py
aios/llm_kernel/llm_classes/base_llm.py
aios/llm_kernel/llm_classes/bed_rock.py
aios/llm_kernel/llm_classes/constant.py
aios/llm_kernel/llm_classes/gemini_llm.py
aios/llm_kernel/llm_classes/gpt_llm.py
aios/llm_kernel/llm_classes/model_registry.py
aios/llm_kernel/llm_classes/ollama_llm.py
aios/llm_kernel/llm_classes/open_llm.py
aios/llm_kernel/llm_classes/vllm.py
aios/memory/README.md
aios/memory/__init__.py
aios/memory/base.py
aios/memory/lru_k_replacer.py
aios/memory/shared_memory.py
aios/memory/single_memory.py
aios/scheduler/README.md
aios/scheduler/__init__.py
aios/scheduler/base.py
aios/scheduler/fifo_scheduler.py
aios/scheduler/rr_scheduler.py
aios/storage/README.md
aios/storage/__init__.py
aios/storage/base.py
aios/storage/db_storage.py
aios/storage/file_storage.py
aios/utils/README.md
aios/utils/__init__.py
aios/utils/calculator.py
aios/utils/compressor.py
aios/utils/logger.py
aios/utils/utils.py
aios/utils/commands/top.py
aioskernel-0.0.1b1.dist-info/METADATA
aioskernel-0.0.1b1.dist-info/WHEEL
aioskernel-0.0.1b1.dist-info/licenses/LICENSE
aioskernel-0.0.1b1.dist-info/RECORD
