Metadata-Version: 2.3
Name: aioskernel
Version: 0.0.1b1
Summary: AIOS: LLM Agent Operating System
Project-URL: Homepage, https://github.com/agiresearch/AIOS
Project-URL: Repository, https://github.com/agiresearch/AIOS.git
License: MIT License
License-File: LICENSE
Keywords: llm,os
Classifier: Development Status :: 3 - Alpha
Classifier: Intended Audience :: Developers
Classifier: License :: OSI Approved :: MIT License
Classifier: Programming Language :: Python :: 3
Classifier: Programming Language :: Python :: 3.9
Classifier: Programming Language :: Python :: 3.10
Classifier: Programming Language :: Python :: 3.11
Classifier: Topic :: Software Development :: Libraries :: Python Modules
Requires-Python: >=3.9
Requires-Dist: click==8.1.7
Requires-Dist: google-api-python-client==2.123.0
Requires-Dist: googlemaps==4.10.0
Requires-Dist: ollama==0.1.7
Requires-Dist: openai==1.20.0
Requires-Dist: pandas==2.2.2
Requires-Dist: protobuf==4.25.3
Requires-Dist: pydantic==2.7.0
Requires-Dist: pympler==1.0.1
Requires-Dist: pyopenagi
Requires-Dist: vllm
